pyffmpeg/__init__.py
pyffmpeg/_compat.py
pyffmpeg/_run.py
pyffmpeg/_utils.py
pyffmpeg/errors.py
pyffmpeg/generated_filters.py
pyffmpeg/generator.py
pyffmpeg/io.py
pyffmpeg/node.py
pyffmpeg/parser.py
pyffmpeg/probe.py
pyffmpeg/script.py
pyffmpeg/sources.py
wut_ffmpeg-0.1.1.dist-info/METADATA
wut_ffmpeg-0.1.1.dist-info/WHEEL
wut_ffmpeg-0.1.1.dist-info/licenses/LICENSE
wut_ffmpeg-0.1.1.dist-info/RECORD
