Metadata-Version: 2.4
Name: wut-ffmpeg
Version: 0.1.1
Summary: A modern, type-safe Python wrapper for FFmpeg
License: MIT
License-File: LICENSE
Keywords: audio,ffmpeg,multimedia,processing,video
Requires-Python: >=3.13
Requires-Dist: jinja2>=3.1.6
Requires-Dist: pytest-mock>=3.15.1
Requires-Dist: pytest>=8.4.2
